[
  {
    "id": 1,
    "nome": "Fundação Bradesco",
    "tipo": "Gratuito",
    "area": "Tecnologia",
    "descricao": "Cursos gratuitos com certificado.",
    "link": "https://www.ev.org.br/"
  },
  {
    "id": 2,
    "nome": "Sebrae",
    "tipo": "Gratuito e pago",
    "area": "Negócios",
    "descricao": "Cursos de empreendedorismo.",
    "link": "https://sebrae.com.br/"
  },
  {
    "id": 3,
    "nome": "SENAI",
    "tipo": "Técnico",
    "area": "Indústria",
    "descricao": "Cursos técnicos e profissionalizantes.",
    "link": "https://play.senai.br/"
  },
  {
    "id": 4,
    "nome": "Coursera",
    "tipo": "Pago",
    "area": "Tecnologia",
    "descricao": "Cursos de universidades e empresas conhecidas.",
    "link": "https://www.coursera.org/"
  }
]